<?xml version="1.0" encoding="UTF-8"?>
<panorama id="node1" apprev="18080" appversion="6.1.13" hideabout="1">
  <input levelbiashidpi="1.000" width="2048" levelbias="0.400" overlap="1" height="2048" leveltileurl="tiles/node1/cf_%c/l_%l/c_%x/tile_%y.jpg" leveltilesize="510" levelingpitch="0" levelingroll="0">
    <level preload="0" predecode="0" width="2048" height="2048"/>
    <level preload="0" predecode="0" width="1024" height="1024"/>
    <level preload="0" predecode="0" width="512" height="512"/>
    <level preload="1" predecode="1" width="256" height="256"/>
    <preview strip="1" color="0x808080"/>
  </input>
  <view pannorth="0" fovmode="0">
    <start projection="4" pan="7.3608" fov="81.2099" tilt="-0.351033"/>
    <flyin projection="9" pan="0" fov="170" tilt="-90"/>
    <min pan="0" fovpixel="2" tilt="-90"/>
    <max scaletofit="1" pan="360" fov="120" fovstereographic="270" fovfisheye="360" tilt="90"/>
  </view>
  <userdata source="" heading="0" comment="" description="" info="" tags="Renders" copyright="" datetime="" longitude="" customnodeid="" nodeid="node1" latitude="" author="" title=""/>
  <hotspots wordwrap="1" width="180" height="20">
    <label textalpha="1" bordercolor="0x000000" wordwrap="1" borderalpha="1" enabled="1" width="180" textcolor="0x000000" backgroundcolor="0xffffff" height="20" border="1" backgroundalpha="1" background="1" borderradius="1"/>
    <polystyle bordercolor="0x0000ff" borderalpha="1" backgroundcolor="0x0000ff" mode="0" backgroundalpha="0.25098" handcursor="1"/>
  </hotspots>
  <media>
    <image id="Element01" rotz="-107.000" clickmode="0" pan="-249.310" rotx="0.000" stretch="1.000" width="716" height="720" fov="14.063" roty="0.000" handcursor="0" tilt="89.270">
      <source url="media/RB logo.jpg"/>
    </image>
  </media>
  <transition blendtime="1" type="crossdissolve" zoomafteroutfov="20" zoomin="0" enabled="1" blendcolor="0x000000" zoomoutpause="1" zoomafterinfov="90" zoomfov="20" zoomout="0" zoomspeed="2" softedge="0"/>
  <animation useinautorotation="0" syncanimationwithvideo="0" animsequence="Animation01"/>
  <control sensitivity="8" speedwheel="1" contextvr="1" lockedmouse="0" invertwheel="0" lockedkeyboardzoom="0" lockedwheel="0" dblclickfullscreen="0" contextfullscreen="1" rubberband="0" hideabout="1" lockedkeyboard="0" invertcontrol="1" contextprojections="0" simulatemass="1"/>
</panorama>
